honeydb_ai/__init__.py
honeydb_ai/configuration.py
honeydb_ai/llm_client.py
honeydb_ai/load_app.py
honeydb_ai/main.py
honeydb_mcp_client/__init__.py
honeydb_mcp_client/configuration.py
honeydb_mcp_client/llm_client.py
honeydb_mcp_client/load_app.py
honeydb_mcp_client/main.py
honeydb_ai-0.1.1.dist-info/METADATA
honeydb_ai-0.1.1.dist-info/WHEEL
honeydb_ai-0.1.1.dist-info/entry_points.txt
honeydb_ai-0.1.1.dist-info/top_level.txt
honeydb_ai-0.1.1.dist-info/RECORD
